webdownloader/__init__.py
webdownloader/downloader.py
webdownloader-0.1.dist-info/LICENSE
webdownloader-0.1.dist-info/METADATA
webdownloader-0.1.dist-info/WHEEL
webdownloader-0.1.dist-info/top_level.txt
webdownloader-0.1.dist-info/RECORD
