Metadata-Version: 2.1
Name: webdownloader
Version: 0.1
Summary: webdownloader is a tool for web data extraction
Home-page: http://github.com/devStarkes/webdownloader
Author: Starkes org.
Author-email: devStarkes@gmail.com
License: MIT
Keywords: webdownloader downloder web extraction parsing scraping mining
Platform: UNKNOWN
Classifier: Programming Language :: Python
Classifier: License :: OSI Approved :: MIT License
Classifier: Operating System :: OS Independent
Classifier: Development Status :: 4 - Beta
Classifier: Intended Audience :: Developers
Classifier: Topic :: Internet :: WWW/HTTP
Classifier: Topic :: Internet :: WWW/HTTP :: Site Management
Requires-Dist: validators
Requires-Dist: requests
Requires-Dist: requests-html
